voidgame.py
voidgame-1.1.dist-info/LICENSE
voidgame-1.1.dist-info/METADATA
voidgame-1.1.dist-info/WHEEL
voidgame-1.1.dist-info/top_level.txt
voidgame-1.1.dist-info/RECORD
